{
    "Watching": [
        {
            "title": {
                "english": "BOCCHI THE ROCK!",
                "romaji": "Bocchi the Rock!"
            },
            "cover": {
                "url": "https://s4.anilist.co/file/anilistcdn/media/anime/cover/large/bx130003-5Y8rYzg982sq.png",
                "color": "#e4bb50"
            },
            "banner": "https://s4.anilist.co/file/anilistcdn/media/anime/banner/130003-Ht7myAxpdNPo.jpg",
            "genres": [
                "Comedy",
                "Music",
                "Slice of Life"
            ],
            "type": "TV",
            "episodes": 12,
            "isAdult": false,
            "progress": 11,
            "score": 84,
            "notes": ""
        },
        {
            "title": {
                "english": "Violet Evergarden",
                "romaji": "Violet Evergarden"
            },
            "cover": {
                "url": "https://s4.anilist.co/file/anilistcdn/media/anime/cover/large/nx21827-10F6m50H4GJK.png",
                "color": "#3586e4"
            },
            "banner": "https://s4.anilist.co/file/anilistcdn/media/anime/banner/21827-ROucgYiiiSpR.jpg",
            "genres": [
                "Drama",
                "Fantasy",
                "Slice of Life"
            ],
            "type": "TV",
            "episodes": 13,
            "isAdult": false,
            "progress": 1,
            "score": 100,
            "notes": ""
        }],
        "Completed": [
            {
                "title": {
                    "english": "Wandering Witch: The Journey of Elaina",
                    "romaji": "Majo no Tabitabi"
                },
                "cover": {
                    "url": "https://s4.anilist.co/file/anilistcdn/media/anime/cover/large/bx112609-dbpOh4fdXAlC.jpg",
                    "color": "#4393e4"
                },
                "banner": "https://s4.anilist.co/file/anilistcdn/media/anime/banner/112609-P969sQ0jIU6S.jpg",
                "genres": [
                    "Adventure",
                    "Fantasy",
                    "Slice of Life"
                ],
                "type": "TV",
                "episodes": 12,
                "isAdult": false,
                "progress": 12,
                "score": 90,
                "notes": ""
            },
            {
                "title": {
                    "english": "BOFURI: I Don't Want to Get Hurt, so I'll Max Out My Defense.",
                    "romaji": "Itai no wa Iya nano de Bougyoryoku ni Kyokufuri Shitai to Omoimasu."
                },
                "cover": {
                    "url": "https://s4.anilist.co/file/anilistcdn/media/anime/cover/large/bx106479-JmPk1F5ubMtm.png",
                    "color": "#1ac9d6"
                },
                "banner": "https://s4.anilist.co/file/anilistcdn/media/anime/banner/106479-G1rExJ4m8Be3.jpg",
                "genres": [
                    "Action",
                    "Adventure",
                    "Comedy",
                    "Fantasy",
                    "Slice of Life"
                ],
                "type": "TV",
                "episodes": 12,
                "isAdult": false,
                "progress": 12,
                "score": 76,
                "notes": ""
            },
            {
                "title": {
                    "english": "I've Been Killing Slimes for 300 Years and Maxed Out My Level",
                    "romaji": "Slime Taoshite 300-nen, Shiranai Uchi ni Level Max ni Nattemashita"
                },
                "cover": {
                    "url": "https://s4.anilist.co/file/anilistcdn/media/anime/cover/large/bx112608-T3OKdLhxYUfe.png",
                    "color": "#5dc9e4"
                },
                "banner": "https://s4.anilist.co/file/anilistcdn/media/anime/banner/112608-MGv0rMEhEWq5.jpg",
                "genres": [
                    "Adventure",
                    "Comedy",
                    "Fantasy",
                    "Slice of Life"
                ],
                "type": "TV",
                "episodes": 12,
                "isAdult": false,
                "progress": 12,
                "score": 68,
                "notes": ""
            }
        ],
        "Planning": [
            {
                "title": {
                    "english": "Chainsaw Man",
                    "romaji": "Chainsaw Man"
                },
                "cover": {
                    "url": "https://s4.anilist.co/file/anilistcdn/media/anime/cover/large/bx127230-FlochcFsyoF4.png",
                    "color": "#6b1a1a"
                },
                "banner": "https://s4.anilist.co/file/anilistcdn/media/anime/banner/127230-uv8EA5WiTc7d.jpg",
                "genres": [
                    "Action",
                    "Comedy",
                    "Drama",
                    "Horror",
                    "Supernatural"
                ],
                "type": "TV",
                "episodes": 12,
                "isAdult": false,
                "progress": null,
                "score": null,
                "notes": ""
            },
            {
                "title": {
                    "english": "Date A Live IV",
                    "romaji": "Date A Live IV"
                },
                "cover": {
                    "url": "https://s4.anilist.co/file/anilistcdn/media/anime/cover/large/bx116605-uzDakXnaZ1OW.jpg",
                    "color": "#e45d43"
                },
                "banner": "https://s4.anilist.co/file/anilistcdn/media/anime/banner/116605-qmByNsRP3c53.jpg",
                "genres": [
                    "Comedy",
                    "Ecchi",
                    "Mecha",
                    "Romance",
                    "Sci-Fi"
                ],
                "type": "TV",
                "episodes": 12,
                "isAdult": false,
                "progress": null,
                "score": null,
                "notes": ""
            }
        ]
    }